nested_argparse/__init__.py
nested_argparse/nested_argparse.py
nested_argparse-0.1.2.dist-info/LICENSE
nested_argparse-0.1.2.dist-info/METADATA
nested_argparse-0.1.2.dist-info/WHEEL
nested_argparse-0.1.2.dist-info/top_level.txt
nested_argparse-0.1.2.dist-info/RECORD
