Metadata-Version: 2.1
Name: nested-argparse
Version: 0.1.2
Summary: A python module that extends argparser to create nested namespace trees for subparsers.
Home-page: UNKNOWN
Author: Stephen Zhao
Author-email: mail@zhaostephen.com
License: MIT License
Keywords: argparse,nested,namespace,subparser,conflict,parser,cli,command,subcommand
Platform: UNKNOWN
Classifier: Development Status :: 2 - Pre-Alpha
Classifier: Intended Audience :: Developers
Classifier: Programming Language :: Python :: 3
Classifier: License :: OSI Approved :: MIT License
Classifier: Operating System :: OS Independent
Classifier: Topic :: Software Development :: Libraries :: Python Modules
Classifier: Topic :: Utilities
Requires-Python: >=3.6
